{
  "generated_by": "analysis/export_measurement_cube_v7a.py",
  "generated_at_utc": "2026-04-29T16:42:56+00:00",
  "protocol_name": "v7a_hm_measurement_cube",
  "development_only": true,
  "shadow_or_final_used": false,
  "shadow_seeds_excluded": true,
  "project_root": "//?/UNC/wsl.localhost/Ubuntu-22.04/home/dyd/geant4-projects/xrt_sorter/release/xrt_sorter_public_undergrad_repo_20260426",
  "raw_dirs": [
    "build/material_sorting_runs/v6c_hm_source_design"
  ],
  "output_dir": "results/accuracy_v3/v7a_hm_measurement_cube_smoke",
  "photon_budget": 5000,
  "grid_bins": 8,
  "materials": [
    "Hematite",
    "Magnetite"
  ],
  "train_seeds": [
    2101,
    2102,
    2103,
    2104,
    2105,
    2106,
    2107,
    2108,
    2109,
    2110,
    2111,
    2112
  ],
  "validation_seeds": [
    2201,
    2202,
    2203,
    2204,
    2205,
    2206
  ],
  "shadow_seeds": [
    2301,
    2302,
    2303,
    2304,
    2305,
    2306
  ],
  "source_ids": [
    "mono_50kev_normal_narrow",
    "mono_70kev_normal_narrow"
  ],
  "detectors": [
    "transmission",
    "side_scatter"
  ],
  "channels": [
    "hit_rate",
    "energy_mean_keV",
    "tail120_rate",
    "primary_rate",
    "direct_primary_rate",
    "scattered_primary_rate",
    "theta_mean_deg"
  ],
  "records_used": 8,
  "samples": 8,
  "tensor_shape": [
    8,
    2,
    2,
    8,
    8,
    7
  ],
  "feature_count": 1792,
  "split_counts": {
    "train": 4,
    "validation": 4
  },
  "software": {
    "python": "3.12.13",
    "pandas": "3.0.1",
    "numpy": "2.3.5"
  }
}
